elicitlabs/__init__.py
elicitlabs/_base_client.py
elicitlabs/_client.py
elicitlabs/_compat.py
elicitlabs/_constants.py
elicitlabs/_exceptions.py
elicitlabs/_files.py
elicitlabs/_models.py
elicitlabs/_qs.py
elicitlabs/_resource.py
elicitlabs/_response.py
elicitlabs/_streaming.py
elicitlabs/_types.py
elicitlabs/_version.py
elicitlabs/py.typed
elicitlabs/_utils/__init__.py
elicitlabs/_utils/_compat.py
elicitlabs/_utils/_datetime_parse.py
elicitlabs/_utils/_logs.py
elicitlabs/_utils/_proxy.py
elicitlabs/_utils/_reflection.py
elicitlabs/_utils/_resources_proxy.py
elicitlabs/_utils/_streams.py
elicitlabs/_utils/_sync.py
elicitlabs/_utils/_transform.py
elicitlabs/_utils/_typing.py
elicitlabs/_utils/_utils.py
elicitlabs/lib/.keep
elicitlabs/resources/__init__.py
elicitlabs/resources/health.py
elicitlabs/resources/inference.py
elicitlabs/resources/modal.py
elicitlabs/resources/personas.py
elicitlabs/resources/users.py
elicitlabs/resources/auth/__init__.py
elicitlabs/resources/auth/auth.py
elicitlabs/resources/auth/keys.py
elicitlabs/resources/data/__init__.py
elicitlabs/resources/data/data.py
elicitlabs/resources/data/job.py
elicitlabs/types/__init__.py
elicitlabs/types/data_ingest_params.py
elicitlabs/types/data_ingest_response.py
elicitlabs/types/inference_generate_completion_params.py
elicitlabs/types/inference_generate_completion_response.py
elicitlabs/types/inference_generate_persona_chat_params.py
elicitlabs/types/inference_generate_persona_chat_response.py
elicitlabs/types/modal_learn_params.py
elicitlabs/types/modal_learn_response.py
elicitlabs/types/modal_query_params.py
elicitlabs/types/modal_query_response.py
elicitlabs/types/persona_create_params.py
elicitlabs/types/persona_create_response.py
elicitlabs/types/persona_list_response.py
elicitlabs/types/persona_retrieve_response.py
elicitlabs/types/user_create_or_get_params.py
elicitlabs/types/user_create_or_get_response.py
elicitlabs/types/auth/__init__.py
elicitlabs/types/auth/key_create_params.py
elicitlabs-0.5.0.dist-info/METADATA
elicitlabs-0.5.0.dist-info/WHEEL
elicitlabs-0.5.0.dist-info/licenses/LICENSE
elicitlabs-0.5.0.dist-info/RECORD
